EM/__init__.py
EM/GPIO/99-gpio.rules
EM/GPIO/__init__.py
EM/GPIO/gpio.py
EM/GPIO/gpio_event.py
EM/GPIO/gpio_pin_data.py
RPi/__init__.py
RPi/GPIO/__init__.py
EM.GPIO-0.0.6.dist-info/LICENSE.txt
EM.GPIO-0.0.6.dist-info/METADATA
EM.GPIO-0.0.6.dist-info/WHEEL
EM.GPIO-0.0.6.dist-info/top_level.txt
EM.GPIO-0.0.6.dist-info/RECORD
