Metadata-Version: 2.1
Name: EM.GPIO
Version: 0.0.6
Summary: A module to control EM GPIO channels
Home-page: https://github.com/NVIDIA/jetson-gpio
Author: Jarius
Author-email: jarius@163.com
License: MIT
Keywords: EM GPIO
Platform: UNKNOWN
Classifier: Operating System :: POSIX :: Linux
Classifier: License :: OSI Approved :: MIT License
Classifier: Intended Audience :: Developers
Classifier: Programming Language :: Python :: 2.7
Classifier: Programming Language :: Python :: 3
Classifier: Topic :: Software Development
Classifier: Topic :: System :: Hardware
License-File: LICENSE.txt
